//*******************************************************************//
//*           Automatically Generated File Please Don't Edit!       *//
//*******************************************************************//


//Any  required modification mail eslam@gmx.de /


#ifndef e_include_H_
	#define e_include_H_




	#include"./inst/000---nop.h"
	#include"./inst/001---aconst_null.h"
	#include"./inst/002---iconst_m1.h"
	#include"./inst/003---iconst_0.h"
	#include"./inst/004---iconst_1.h"
	#include"./inst/005---iconst_2.h"
	#include"./inst/006---iconst_3.h"
	#include"./inst/007---iconst_4.h"
	#include"./inst/008---iconst_5.h"
	#include"./inst/009---lconst_0.h"
	#include"./inst/010---lconst_1.h"
	#include"./inst/011---fconst_0.h"
	#include"./inst/012---fconst_1.h"
	#include"./inst/013---fconst_2.h"
	#include"./inst/014---dconst_0.h"
	#include"./inst/015---dconst_1.h"
	#include"./inst/016---bipush.h"
	#include"./inst/017---sipush.h"
	#include"./inst/018---ldc.h"
	#include"./inst/019---ldc_w.h"
	#include"./inst/020---ldc2_w.h"
	#include"./inst/021---iload.h"
	#include"./inst/022---lload.h"
	#include"./inst/023---fload.h"
	#include"./inst/024---dload.h"
	#include"./inst/025---aload.h"
	#include"./inst/026---iload_0.h"
	#include"./inst/027---iload_1.h"
	#include"./inst/028---iload_2.h"
	#include"./inst/029---iload_3.h"
	#include"./inst/030---lload_0.h"
	#include"./inst/031---lload_1.h"
	#include"./inst/032---lload_2.h"
	#include"./inst/033---lload_3.h"
	#include"./inst/034---fload_0.h"
	#include"./inst/035---fload_1.h"
	#include"./inst/036---fload_2.h"
	#include"./inst/037---fload_3.h"
	#include"./inst/038---dload_0.h"
	#include"./inst/039---dload_1.h"
	#include"./inst/040---dload_2.h"
	#include"./inst/041---dload_3.h"
	#include"./inst/042---aload_0.h"
	#include"./inst/043---aload_1.h"
	#include"./inst/044---aload_2.h"
	#include"./inst/045---aload_3.h"
	#include"./inst/046---iaload.h"
	#include"./inst/047---laload.h"
	#include"./inst/048---faload.h"
	#include"./inst/049---daload.h"
	#include"./inst/050---aaload.h"
	#include"./inst/051---baload.h"
	#include"./inst/052---caload.h"
	#include"./inst/053---saload.h"
	#include"./inst/054---istore.h"
	#include"./inst/055---lstore.h"
	#include"./inst/056---fstore.h"
	#include"./inst/057---dstore.h"
	#include"./inst/058---astore.h"
	#include"./inst/059---istore_0.h"
	#include"./inst/060---istore_1.h"
	#include"./inst/061---istore_2.h"
	#include"./inst/062---istore_3.h"
	#include"./inst/063---lstore_0.h"
	#include"./inst/064---lstore_1.h"
	#include"./inst/065---lstore_2.h"
	#include"./inst/066---lstore_3.h"
	#include"./inst/067---fstore_0.h"
	#include"./inst/068---fstore_1.h"
	#include"./inst/069---fstore_2.h"
	#include"./inst/070---fstore_3.h"
	#include"./inst/071---dstore_0.h"
	#include"./inst/072---dstore_1.h"
	#include"./inst/073---dstore_2.h"
	#include"./inst/074---dstore_3.h"
	#include"./inst/075---astore_0.h"
	#include"./inst/076---astore_1.h"
	#include"./inst/077---astore_2.h"
	#include"./inst/078---astore_3.h"
	#include"./inst/079---iastore.h"
	#include"./inst/080---lastore.h"
	#include"./inst/081---fastore.h"
	#include"./inst/082---dastore.h"
	#include"./inst/083---aastore.h"
	#include"./inst/084---bastore.h"
	#include"./inst/085---castore.h"
	#include"./inst/086---sastore.h"
	#include"./inst/087---pop.h"
	#include"./inst/088---pop2.h"
	#include"./inst/089---dup.h"
	#include"./inst/090---dup_x1.h"
	#include"./inst/091---dup_x2.h"
	#include"./inst/092---dup2.h"
	#include"./inst/093---dup2_x1.h"
	#include"./inst/094---dup2_x2.h"
	#include"./inst/095---swap.h"
	#include"./inst/096---iadd.h"
	#include"./inst/097---ladd.h"
	#include"./inst/098---fadd.h"
	#include"./inst/099---dadd.h"
	#include"./inst/100---isub.h"
	#include"./inst/101---lsub.h"
	#include"./inst/102---fsub.h"
	#include"./inst/103---dsub.h"
	#include"./inst/104---imul.h"
	#include"./inst/105---lmul.h"
	#include"./inst/106---fmul.h"
	#include"./inst/107---dmul.h"
	#include"./inst/108---idiv.h"
	#include"./inst/109---ldiv.h"
	#include"./inst/110---fdiv.h"
	#include"./inst/111---ddiv.h"
	#include"./inst/112---irem.h"
	#include"./inst/113---lrem.h"
	#include"./inst/114---frem.h"
	#include"./inst/115---drem.h"
	#include"./inst/116---ineg.h"
	#include"./inst/117---lneg.h"
	#include"./inst/118---fneg.h"
	#include"./inst/119---dneg.h"
	#include"./inst/120---ishl.h"
	#include"./inst/121---lshl.h"
	#include"./inst/122---ishr.h"
	#include"./inst/123---lshr.h"
	#include"./inst/124---iushr.h"
	#include"./inst/125---lushr.h"
	#include"./inst/126---iand.h"
	#include"./inst/127---land.h"
	#include"./inst/128---ior.h"
	#include"./inst/129---lor.h"
	#include"./inst/130---ixor.h"
	#include"./inst/131---lxor.h"
	#include"./inst/132---iinc.h"
	#include"./inst/133---i2l.h"
	#include"./inst/134---i2f.h"
	#include"./inst/135---i2d.h"
	#include"./inst/136---l2i.h"
	#include"./inst/137---l2f.h"
	#include"./inst/138---l2d.h"
	#include"./inst/139---f2i.h"
	#include"./inst/140---f2l.h"
	#include"./inst/141---f2d.h"
	#include"./inst/142---d2i.h"
	#include"./inst/143---d2l.h"
	#include"./inst/144---d2f.h"
	#include"./inst/145---i2b.h"
	#include"./inst/146---i2c.h"
	#include"./inst/147---i2s.h"
	#include"./inst/148---lcmp.h"
	#include"./inst/149---fcmpl.h"
	#include"./inst/150---fcmpg.h"
	#include"./inst/151---dcmpl.h"
	#include"./inst/152---dcmpg.h"
	#include"./inst/153---ifeq.h"
	#include"./inst/154---ifne.h"
	#include"./inst/155---iflt.h"
	#include"./inst/156---ifge.h"
	#include"./inst/157---ifgt.h"
	#include"./inst/158---ifle.h"
	#include"./inst/159---if_icmpeq.h"
	#include"./inst/160---if_icmpne.h"
	#include"./inst/161---if_icmplt.h"
	#include"./inst/162---if_icmpge.h"
	#include"./inst/163---if_icmpgt.h"
	#include"./inst/164---if_icmple.h"
	#include"./inst/165---if_acmpeq.h"
	#include"./inst/166---if_acmpne.h"
	#include"./inst/167---goto.h"
	#include"./inst/168---jsr.h"
	#include"./inst/169---ret.h"
	#include"./inst/170---tableswitch.h"
	#include"./inst/171---lookupswitch.h"
	#include"./inst/172---ireturn.h"
	#include"./inst/173---lreturn.h"
	#include"./inst/174---freturn.h"
	#include"./inst/175---dreturn.h"
	#include"./inst/176---areturn.h"
	#include"./inst/177---return.h"
	#include"./inst/178---getstatic.h"
	#include"./inst/179---putstatic.h"
	#include"./inst/180---getfield.h"
	#include"./inst/181---putfield.h"
	#include"./inst/182---invokevirtual.h"
	#include"./inst/183---invokespecial.h"
	#include"./inst/184---invokestatic.h"
	#include"./inst/185---invokeinterface.h"
	#include"./inst/186---xxxunusedxxx1.h"
	#include"./inst/187---new.h"
	#include"./inst/188---newarray.h"
	#include"./inst/189---anewarray.h"
	#include"./inst/190---arraylength.h"
	#include"./inst/191---athrow.h"
	#include"./inst/192---checkcast.h"
	#include"./inst/193---instanceof.h"
	#include"./inst/194---monitorenter.h"
	#include"./inst/195---monitorexit.h"
	#include"./inst/196---wide.h"
	#include"./inst/197---multianewarray.h"
	#include"./inst/198---ifnull.h"
	#include"./inst/199---ifnonnull.h"
	#include"./inst/200---goto_w.h"
	#include"./inst/201---jsr_w.h"
	#include"./inst/202---breakpoint.h"
	#include"./inst/254---impdep1.h"
	#include"./inst/255---impdep2.h"
#endif // e_include_H_

