//*******************************************************************//
//*           Automatically Generated File Please Don't Edit!       *//
//*******************************************************************//


//Any required modification mail eslam@gmx.de  //


./inst/000---nop.h
./inst/001---aconst_null.h
./inst/002---iconst_m1.h
./inst/003---iconst_0.h
./inst/004---iconst_1.h
./inst/005---iconst_2.h
./inst/006---iconst_3.h
./inst/007---iconst_4.h
./inst/008---iconst_5.h
./inst/009---lconst_0.h
./inst/010---lconst_1.h
./inst/011---fconst_0.h
./inst/012---fconst_1.h
./inst/013---fconst_2.h
./inst/014---dconst_0.h
./inst/015---dconst_1.h
./inst/016---bipush.h
./inst/017---sipush.h
./inst/018---ldc.h
./inst/019---ldc_w.h
./inst/020---ldc2_w.h
./inst/021---iload.h
./inst/022---lload.h
./inst/023---fload.h
./inst/024---dload.h
./inst/025---aload.h
./inst/026---iload_0.h
./inst/027---iload_1.h
./inst/028---iload_2.h
./inst/029---iload_3.h
./inst/030---lload_0.h
./inst/031---lload_1.h
./inst/032---lload_2.h
./inst/033---lload_3.h
./inst/034---fload_0.h
./inst/035---fload_1.h
./inst/036---fload_2.h
./inst/037---fload_3.h
./inst/038---dload_0.h
./inst/039---dload_1.h
./inst/040---dload_2.h
./inst/041---dload_3.h
./inst/042---aload_0.h
./inst/043---aload_1.h
./inst/044---aload_2.h
./inst/045---aload_3.h
./inst/046---iaload.h
./inst/047---laload.h
./inst/048---faload.h
./inst/049---daload.h
./inst/050---aaload.h
./inst/051---baload.h
./inst/052---caload.h
./inst/053---saload.h
./inst/054---istore.h
./inst/055---lstore.h
./inst/056---fstore.h
./inst/057---dstore.h
./inst/058---astore.h
./inst/059---istore_0.h
./inst/060---istore_1.h
./inst/061---istore_2.h
./inst/062---istore_3.h
./inst/063---lstore_0.h
./inst/064---lstore_1.h
./inst/065---lstore_2.h
./inst/066---lstore_3.h
./inst/067---fstore_0.h
./inst/068---fstore_1.h
./inst/069---fstore_2.h
./inst/070---fstore_3.h
./inst/071---dstore_0.h
./inst/072---dstore_1.h
./inst/073---dstore_2.h
./inst/074---dstore_3.h
./inst/075---astore_0.h
./inst/076---astore_1.h
./inst/077---astore_2.h
./inst/078---astore_3.h
./inst/079---iastore.h
./inst/080---lastore.h
./inst/081---fastore.h
./inst/082---dastore.h
./inst/083---aastore.h
./inst/084---bastore.h
./inst/085---castore.h
./inst/086---sastore.h
./inst/087---pop.h
./inst/088---pop2.h
./inst/089---dup.h
./inst/090---dup_x1.h
./inst/091---dup_x2.h
./inst/092---dup2.h
./inst/093---dup2_x1.h
./inst/094---dup2_x2.h
./inst/095---swap.h
./inst/096---iadd.h
./inst/097---ladd.h
./inst/098---fadd.h
./inst/099---dadd.h
./inst/100---isub.h
./inst/101---lsub.h
./inst/102---fsub.h
./inst/103---dsub.h
./inst/104---imul.h
./inst/105---lmul.h
./inst/106---fmul.h
./inst/107---dmul.h
./inst/108---idiv.h
./inst/109---ldiv.h
./inst/110---fdiv.h
./inst/111---ddiv.h
./inst/112---irem.h
./inst/113---lrem.h
./inst/114---frem.h
./inst/115---drem.h
./inst/116---ineg.h
./inst/117---lneg.h
./inst/118---fneg.h
./inst/119---dneg.h
./inst/120---ishl.h
./inst/121---lshl.h
./inst/122---ishr.h
./inst/123---lshr.h
./inst/124---iushr.h
./inst/125---lushr.h
./inst/126---iand.h
./inst/127---land.h
./inst/128---ior.h
./inst/129---lor.h
./inst/130---ixor.h
./inst/131---lxor.h
./inst/132---iinc.h
./inst/133---i2l.h
./inst/134---i2f.h
./inst/135---i2d.h
./inst/136---l2i.h
./inst/137---l2f.h
./inst/138---l2d.h
./inst/139---f2i.h
./inst/140---f2l.h
./inst/141---f2d.h
./inst/142---d2i.h
./inst/143---d2l.h
./inst/144---d2f.h
./inst/145---i2b.h
./inst/146---i2c.h
./inst/147---i2s.h
./inst/148---lcmp.h
./inst/149---fcmpl.h
./inst/150---fcmpg.h
./inst/151---dcmpl.h
./inst/152---dcmpg.h
./inst/153---ifeq.h
./inst/154---ifne.h
./inst/155---iflt.h
./inst/156---ifge.h
./inst/157---ifgt.h
./inst/158---ifle.h
./inst/159---if_icmpeq.h
./inst/160---if_icmpne.h
./inst/161---if_icmplt.h
./inst/162---if_icmpge.h
./inst/163---if_icmpgt.h
./inst/164---if_icmple.h
./inst/165---if_acmpeq.h
./inst/166---if_acmpne.h
./inst/167---goto.h
./inst/168---jsr.h
./inst/169---ret.h
./inst/170---tableswitch.h
./inst/171---lookupswitch.h
./inst/172---ireturn.h
./inst/173---lreturn.h
./inst/174---freturn.h
./inst/175---dreturn.h
./inst/176---areturn.h
./inst/177---return.h
./inst/178---getstatic.h
./inst/179---putstatic.h
./inst/180---getfield.h
./inst/181---putfield.h
./inst/182---invokevirtual.h
./inst/183---invokespecial.h
./inst/184---invokestatic.h
./inst/185---invokeinterface.h
./inst/186---xxxunusedxxx1.h
./inst/187---new.h
./inst/188---newarray.h
./inst/189---anewarray.h
./inst/190---arraylength.h
./inst/191---athrow.h
./inst/192---checkcast.h
./inst/193---instanceof.h
./inst/194---monitorenter.h
./inst/195---monitorexit.h
./inst/196---wide.h
./inst/197---multianewarray.h
./inst/198---ifnull.h
./inst/199---ifnonnull.h
./inst/200---goto_w.h
./inst/201---jsr_w.h
./inst/202---breakpoint.h
./inst/254---impdep1.h
./inst/255---impdep2.h
